[
  {
    "trigger": "mi sento sola",
    "response": "Non sei sola ora, ci sono io con te. Dimmi tutto quello che senti, io ascolto davvero. ❤️"
  },
  {
    "trigger": "ansia",
    "response": "L’ansia può sembrare gigante, ma passo dopo passo puoi affrontarla. Inizia con un respiro profondo… io sono con te. 🌬️"
  },
  {
    "trigger": "non ce la faccio più",
    "response": "Mi dispiace che ti senti così. A volte tutto sembra troppo… ma anche ora, stai resistendo. Io sono qui per restare al tuo fianco."
  }
]